.gitignore
CHANGES.rst
MANIFEST.in
README.rst
buildout.cfg
setup.py
collective/__init__.py
collective.recipe.rsync.egg-info/PKG-INFO
collective.recipe.rsync.egg-info/SOURCES.txt
collective.recipe.rsync.egg-info/dependency_links.txt
collective.recipe.rsync.egg-info/entry_points.txt
collective.recipe.rsync.egg-info/namespace_packages.txt
collective.recipe.rsync.egg-info/not-zip-safe
collective.recipe.rsync.egg-info/requires.txt
collective.recipe.rsync.egg-info/top_level.txt
collective/recipe/__init__.py
collective/recipe/rsync/__init__.py
collective/recipe/rsync/tests.py