Metadata-Version: 1.1
Name: collective.recipe.rsync
Version: 2.3.0
Summary: A zc.buildout recipe to copy files from one location        to another via rsync
Home-page: http://collective.github.com/collective.recipe.rsync
Author: Alex Clark
Author-email: aclark@aclark.net
License: ZPL
Keywords: plone rsync
Platform: UNKNOWN
Classifier: Framework :: Buildout
Classifier: Intended Audience :: Developers
Classifier: Topic :: Software Development :: Build Tools
Classifier: Topic :: Software Development :: Libraries :: Python Modules
Classifier: Programming Language :: Python :: 2.7
Classifier: License :: OSI Approved :: Zope Public License
